{"status": "PASS", "META_requiredChecksPassing": true, "GEOM_requiredChecksPassing": true, "META_canonicalNameInMeta": false, "META_licenseImageInZip": false, "META_yearValid": true, "META_isoValid": true, "META_boundaryTypeValid": true, "META_sourceExists": true, "META_releaseTypeValid": true, "META_releaseTypeCorrectFolder": true, "META_licenseValid": true, "META_licenseSourceExists": true, "META_dataSourceExists": true, "GEOM_boundaryNamesColumnExists": true, "GEOM_boundaryNamesFilledIn": true, "GEOM_boundaryISOColumnExists": true, "GEOM_boundaryISOsFilledIn": true, "GEOM_Topology": true, "GEOM_Projection": true, "boundaryID": "NZL-ADM1-nightly", "boundaryISO": "NZL", "boundaryType": "ADM1", "boundaryYear": "2017.0", "boundarySource-1": "NZ Stats", "boundarySource-2": "nan", "boundaryCanonical": "", "boundaryLicense": "Creative Commons Attribution 4.0 International (CC BY 4.0)", "licenseDetail": "Creative Commons Attribution 4.0", "licenseSource": "http//www.stats.govt.nz/about_us/about-this-site/copyright-terms-of-use.aspx", "boundarySourceURL": "http//www.stats.govt.nz/browse_for_stats/Maps_and_geography/Geographic-areas/digital-boundary-files.aspx", "downloadURL": "https://github.com/wmgeolab/gbRelease/raw/master/releaseData/gbOpen/NZL_ADM1.zip"}